crypsdb/crypsdb.py
crypsdb-1.1.2.dist-info/METADATA
crypsdb-1.1.2.dist-info/WHEEL
crypsdb-1.1.2.dist-info/top_level.txt
crypsdb-1.1.2.dist-info/RECORD
