Metadata-Version: 2.1
Name: crypsdb
Version: 1.1.2
Summary: A lightweight JSON-based database system for Python
Home-page: https://github.com/E491K8/crypsDb
Author: Pawan kumar
Author-email: control@vvfin.in
Classifier: Programming Language :: Python :: 3
Classifier: License :: OSI Approved :: MIT License
Classifier: Operating System :: OS Independent
